{
  "list": [
    {
      "name":"expelliarmus",
      "url":"https://expelliarmus.readthedocs.io",
      "desc":"Library for decoding data generated by event cameras to NumPy arrays. Created together with [Gregor Lenz](https://lenzgregor.com)."
    },
    {
      "name":"Tonic",
      "url":"https://tonic.readthedocs.io",
      "desc":"Datasets and transformations for event-based data. Created by [Gregor Lenz](https://lenzgregor.com)."
    },
    {
      "name":"Open Neuromorphic",
      "url":"https://open-neuromorphic.github.io",
      "desc":"Organisation for the open source neuromorphic research. Founded together with [Gregor Lenz](https://lenzgregor.com), [Jason Eshraghian](https://jasoneshraghian.com) and [Charlotte Frenkel](https://chfrenkel.github.io)."
    }
  ]
}
